trial6697_2/__init__.py
trial6697_2-0.0.1.dist-info/METADATA
trial6697_2-0.0.1.dist-info/WHEEL
trial6697_2-0.0.1.dist-info/top_level.txt
trial6697_2-0.0.1.dist-info/RECORD
