Metadata-Version: 2.1
Name: trial6697-2
Version: 0.0.1
Summary: trial
Home-page: UNKNOWN
Author: Antony Kishoare J
Author-email: <a060697.ak@gmail.com>
License: UNKNOWN
Keywords: ee,trial
Platform: UNKNOWN
Classifier: Development Status :: 3 - Alpha
Classifier: Intended Audience :: Education
Classifier: Programming Language :: Python :: 2
Classifier: Programming Language :: Python :: 3
Classifier: Operating System :: MacOS :: MacOS X
Classifier: Operating System :: Microsoft :: Windows
Requires-Dist: earthengine-api
